apiquran/__init__.py
apiquran/alquran/1.json
apiquran/alquran/10.json
apiquran/alquran/100.json
apiquran/alquran/101.json
apiquran/alquran/102.json
apiquran/alquran/103.json
apiquran/alquran/104.json
apiquran/alquran/105.json
apiquran/alquran/106.json
apiquran/alquran/107.json
apiquran/alquran/108.json
apiquran/alquran/109.json
apiquran/alquran/11.json
apiquran/alquran/110.json
apiquran/alquran/111.json
apiquran/alquran/112.json
apiquran/alquran/113.json
apiquran/alquran/114.json
apiquran/alquran/12.json
apiquran/alquran/13.json
apiquran/alquran/14.json
apiquran/alquran/15.json
apiquran/alquran/16.json
apiquran/alquran/17.json
apiquran/alquran/18.json
apiquran/alquran/19.json
apiquran/alquran/2.json
apiquran/alquran/20.json
apiquran/alquran/21.json
apiquran/alquran/22.json
apiquran/alquran/23.json
apiquran/alquran/24.json
apiquran/alquran/25.json
apiquran/alquran/26.json
apiquran/alquran/27.json
apiquran/alquran/28.json
apiquran/alquran/29.json
apiquran/alquran/3.json
apiquran/alquran/30.json
apiquran/alquran/31.json
apiquran/alquran/32.json
apiquran/alquran/33.json
apiquran/alquran/34.json
apiquran/alquran/35.json
apiquran/alquran/36.json
apiquran/alquran/37.json
apiquran/alquran/38.json
apiquran/alquran/39.json
apiquran/alquran/4.json
apiquran/alquran/40.json
apiquran/alquran/41.json
apiquran/alquran/42.json
apiquran/alquran/43.json
apiquran/alquran/44.json
apiquran/alquran/45.json
apiquran/alquran/46.json
apiquran/alquran/47.json
apiquran/alquran/48.json
apiquran/alquran/49.json
apiquran/alquran/5.json
apiquran/alquran/50.json
apiquran/alquran/51.json
apiquran/alquran/52.json
apiquran/alquran/53.json
apiquran/alquran/54.json
apiquran/alquran/55.json
apiquran/alquran/56.json
apiquran/alquran/57.json
apiquran/alquran/58.json
apiquran/alquran/59.json
apiquran/alquran/6.json
apiquran/alquran/60.json
apiquran/alquran/61.json
apiquran/alquran/62.json
apiquran/alquran/63.json
apiquran/alquran/64.json
apiquran/alquran/65.json
apiquran/alquran/66.json
apiquran-1.2.1.dist-info/METADATA
apiquran-1.2.1.dist-info/WHEEL
apiquran-1.2.1.dist-info/RECORD
