Metadata-Version: 2.1
Name: apiquran
Version: 1.2.1
Summary: Al-Quran verse translation in Indonesian and equipped with Juz al-Quran
License: MIT
Keywords: Al-Quran verse translation in Indonesian,apiquran,alquran bahasa indonesia,api al-quran,api alquran,alquran,al-quran
Author: harigro
Author-email: trierbank@gmail.com
Requires-Python: >=3.10,<4.0
Classifier: License :: OSI Approved :: MIT License
Classifier: Programming Language :: Python
Classifier: Programming Language :: Python :: 3
Classifier: Programming Language :: Python :: 3.10
Classifier: Programming Language :: Python :: 3.11
Classifier: Programming Language :: Python :: 3 :: Only
Classifier: Programming Language :: Python :: 3.7
Classifier: Programming Language :: Python :: 3.8
Classifier: Programming Language :: Python :: 3.9
Classifier: Topic :: Software Development :: Libraries :: Python Modules
Project-URL: Documentation, https://github.com/harigro/apiquran
Project-URL: Homepage, https://github.com/harigro/apiquran
Project-URL: Repository, https://github.com/harigro/apiquran
